TheSilent.py
thesilent-0.1.25.dist-info/licenses/LICENSE
thesilent-0.1.25.dist-info/METADATA
thesilent-0.1.25.dist-info/WHEEL
thesilent-0.1.25.dist-info/top_level.txt
thesilent-0.1.25.dist-info/RECORD
